sci_clone/__init__.py
sci_clone/config.py
sci_clone/main.py
sci_clone/util.py
sci_clone-0.4.3.dist-info/LICENSE
sci_clone-0.4.3.dist-info/METADATA
sci_clone-0.4.3.dist-info/WHEEL
sci_clone-0.4.3.dist-info/entry_points.txt
sci_clone-0.4.3.dist-info/top_level.txt
sci_clone-0.4.3.dist-info/RECORD
