Metadata-Version: 2.1
Name: sci-clone
Version: 0.4.3
Summary: A simple tool for cloning from Sci-Hub.
Home-page: https://github.com/f10w3r/sci-clone
Author: f10w3r
Author-email: lifuminster@gmail.com
License: MIT
Keywords: sci-hub sci-clone sci_clone sciclone issn doi paper article journal
Classifier: Intended Audience :: Education
Classifier: Intended Audience :: Science/Research
Classifier: License :: OSI Approved :: MIT License
Classifier: Programming Language :: Python :: 3 :: Only
Classifier: Operating System :: MacOS :: MacOS X
Classifier: Operating System :: Microsoft :: Windows
Classifier: Operating System :: POSIX :: Linux
License-File: LICENSE
Requires-Dist: typer (>=0.6.1)
